murre/__init__.py
murre/dialects.py
murre/download.py
murre/generator.py
murre/normalizer.py
murre/models/readme.txt
murre-1.4.1.dist-info/LICENSE
murre-1.4.1.dist-info/METADATA
murre-1.4.1.dist-info/WHEEL
murre-1.4.1.dist-info/top_level.txt
murre-1.4.1.dist-info/RECORD
