Metadata-Version: 2.1
Name: murre
Version: 1.4.1
Summary: The amazing Murre will normalize non-standard Finnish and Swedish, and dialectalize standard Finnish!
Home-page: https://github.com/mikahama/murre
Author: Mika Hämäläinen
Author-email: mika@flyforpoints.com
License: Apache 2.0
Project-URL: Bug Reports, https://github.com/mikahama/murre/issues
Project-URL: Developer, https://mikakalevi.com/
Keywords: Spoken Finnish,spelling normalization
Classifier: Development Status :: 5 - Production/Stable
Classifier: Intended Audience :: Developers
Classifier: Topic :: Text Processing :: Linguistic
Classifier: Programming Language :: Python :: 3
License-File: LICENSE
Requires-Dist: natas
Requires-Dist: OpenNMT-tf >=2.18.1
Requires-Dist: pyonmttok >=1.23.0
Requires-Dist: tensorflow ==2.4.0
Requires-Dist: tensorflow-addons ==0.12.1
